basacommons/BaseDAO.py
basacommons/Database.py
basacommons/SingletonMeta.py
basacommons/__init__.py
basacommons/alerts.py
basacommons/configloader.py
basacommons-0.0.16.dist-info/LICENSE
basacommons-0.0.16.dist-info/METADATA
basacommons-0.0.16.dist-info/WHEEL
basacommons-0.0.16.dist-info/top_level.txt
basacommons-0.0.16.dist-info/RECORD
