Metadata-Version: 2.1
Name: basacommons
Version: 0.0.16
Summary: Basic project utilities
Home-page: https://github.com/ebasanez/python-commons
Author: Enrique Basañez Mercader
Author-email: enrique.basanez@gmail.com
License: UNKNOWN
Platform: UNKNOWN
Requires-Python: >=3.7
